MANIFEST.in
README.md
setup.py
peatio_client/__init__.py
peatio_client/auth.py
peatio_client/client.py
peatio_client/error.py
peatio_client/streaming_client.py
peatio_client.egg-info/PKG-INFO
peatio_client.egg-info/SOURCES.txt
peatio_client.egg-info/dependency_links.txt
peatio_client.egg-info/not-zip-safe
peatio_client.egg-info/requires.txt
peatio_client.egg-info/top_level.txt