Metadata-Version: 1.0
Name: peatio-client
Version: 0.1.0
Summary: a client library to the bitcoin exchange Peatio
Home-page: UNKNOWN
Author: czheo
Author-email: UNKNOWN
License: LGPL
Keywords: bitcoin peatio yunbi.com
Platform: UNKNOWN
